{
  "formDataSchema": {
    "type": "object",
    "properties": {
      "ministry": {
        "type": "string"
      },
      "anotherThing": {
        "type": "string"
      }
    },
    "required": []
  },
  "formUISchema": {
    "type": "VerticalLayout",
    "elements": [
      {
        "type": "Control",
        "scope": "#/properties/ministry"
      },
      {
        "type": "Control",
        "scope": "#/properties/anotherThing",
        "options": {
          "multi": true
        }
      }
    ]
  }
}
